pandasai_ee/LICENSE
pandasai_ee/__init__.py
pandasai_ee/pipelines/code_execution_engine.py
pandasai_ee/pipelines/enhanced_chat_pipeline.py
pandasai_ee/pipelines/enhanced_code_executor.py
pandasai_enterprise-0.1.0.dist-info/METADATA
pandasai_enterprise-0.1.0.dist-info/WHEEL
pandasai_enterprise-0.1.0.dist-info/RECORD
