Metadata-Version: 2.1
Name: pandasai-enterprise
Version: 0.1.0
Summary: 
Author: Sinaptik Inc
Requires-Python: >=3.9,<4.0
Classifier: Programming Language :: Python :: 3
Classifier: Programming Language :: Python :: 3.9
Classifier: Programming Language :: Python :: 3.10
Classifier: Programming Language :: Python :: 3.11
Classifier: Programming Language :: Python :: 3.12
Requires-Dist: pandasai[all] (>=2.0.35,<3.0.0)
Requires-Dist: pyyaml (>=6.0.1,<7.0.0)
